Metadata-Version: 2.1
Name: TellMeFriday
Version: 0.0.1
Summary: A simple tool based on gtts(google text to speech api)
Home-page: UNKNOWN
Author: C Lokesh Kumar Reddy
Author-email: lokeshkumarreddy.c@gmail.com
License: MIT
Keywords: calculator
Platform: UNKNOWN
Classifier: Development Status :: 5 - Production/Stable
Classifier: Intended Audience :: Education
Classifier: Operating System :: OS Independent
Classifier: License :: OSI Approved :: MIT License
Classifier: Programming Language :: Python :: 3.7
